[
  { "code": "SVK26-G00-GAJAN", "name": "Adam Gajan", "team": "SVK", "jerseyNumber": null, "position": "G", "tier": "C" },
  { "code": "SVK26-G00-HLAVAJ", "name": "Samuel Hlavaj", "team": "SVK", "jerseyNumber": null, "position": "G", "tier": "B" },
  { "code": "SVK26-G00-RABCAN", "name": "Eugen Rabčan", "team": "SVK", "jerseyNumber": null, "position": "G", "tier": "E" },
  { "code": "SVK26-D00-GAJDOS", "name": "František Gajdoš", "team": "SVK", "jerseyNumber": null, "position": "D", "tier": "D" },
  { "code": "SVK26-D00-KNAZKO", "name": "Samuel Kňažko", "team": "SVK", "jerseyNumber": null, "position": "D", "tier": "C" },
  { "code": "SVK26-D00-KOCH", "name": "Patrik Koch", "team": "SVK", "jerseyNumber": null, "position": "D", "tier": "C" },
  { "code": "SVK26-D00-MELISKO", "name": "Jakub Meliško", "team": "SVK", "jerseyNumber": null, "position": "D", "tier": "D" },
  { "code": "SVK26-D00-PETROVI", "name": "Rayen Petrovický", "team": "SVK", "jerseyNumber": null, "position": "D", "tier": "D" },
  { "code": "SVK26-D00-RADIVOJ", "name": "Luka Radivojevič", "team": "SVK", "jerseyNumber": null, "position": "D", "tier": "E" },
  { "code": "SVK26-D00-ROSAND", "name": "Mislav Rosandič", "team": "SVK", "jerseyNumber": null, "position": "D", "tier": "D" },
  { "code": "SVK26-D00-STRBAK", "name": "Maxim Śtrbák", "team": "SVK", "jerseyNumber": null, "position": "D", "tier": "C" },
  { "code": "SVK26-F00-CEDERLE", "name": "Sebastián Čederle", "team": "SVK", "jerseyNumber": null, "position": "F", "tier": "E" },
  { "code": "SVK26-F00-FASKORUD", "name": "Martin Faško-Rudáš", "team": "SVK", "jerseyNumber": null, "position": "F", "tier": "E" },
  { "code": "SVK26-F00-HRIVIK", "name": "Marek Hrivík", "team": "SVK", "jerseyNumber": null, "position": "F", "tier": "C" },
  { "code": "SVK26-F00-KOLLAR", "name": "Andrej Kollár", "team": "SVK", "jerseyNumber": null, "position": "F", "tier": "D" },
  { "code": "SVK26-F00-LACKA", "name": "Jakub Lacka", "team": "SVK", "jerseyNumber": null, "position": "F", "tier": "E" },
  { "code": "SVK26-F00-LISKA", "name": "Adam Liška", "team": "SVK", "jerseyNumber": null, "position": "F", "tier": "D" },
  { "code": "SVK26-F00-MINARIK", "name": "Jakub Minárik", "team": "SVK", "jerseyNumber": null, "position": "F", "tier": "D" },
  { "code": "SVK26-F00-NAUS", "name": "Aurel Nauš", "team": "SVK", "jerseyNumber": null, "position": "F", "tier": "E" },
  { "code": "SVK26-F00-OKULIAR", "name": "Oliver Okuliar", "team": "SVK", "jerseyNumber": null, "position": "F", "tier": "C" },
  { "code": "SVK26-F00-PETRAS", "name": "Šimon Petráš", "team": "SVK", "jerseyNumber": null, "position": "F", "tier": "E" },
  { "code": "SVK26-F00-PETROVS", "name": "Servác Petrovský", "team": "SVK", "jerseyNumber": null, "position": "F", "tier": "C" },
  { "code": "SVK26-F00-KPOSPIS", "name": "Kristián Pospíšil", "team": "SVK", "jerseyNumber": null, "position": "F", "tier": "C" },
  { "code": "SVK26-F00-MPOSPIS", "name": "Martin Pospíšil", "team": "SVK", "jerseyNumber": null, "position": "F", "tier": "B" },
  { "code": "SVK26-F00-SYKORA", "name": "Adam Sýkora", "team": "SVK", "jerseyNumber": null, "position": "F", "tier": "B" }
]
